{
  "id": "master",
  "realm": "master",
  "displayName": "Keycloak",
  "displayNameHtml": "<div class=\"kc-logo-text\"><span>Keycloak spafka</span></div>",
  "notBefore": 0,
  "revokeRefreshToken": false,
  "refreshTokenMaxReuse": 0,
  "accessTokenLifespan": 60,
  "accessTokenLifespanForImplicitFlow": 900,
  "ssoSessionIdleTimeout": 1800,
  "ssoSessionMaxLifespan": 36000,
  "ssoSessionIdleTimeoutRememberMe": 0,
  "ssoSessionMaxLifespanRememberMe": 0,
  "offlineSessionIdleTimeout": 2592000,
  "offlineSessionMaxLifespanEnabled": false,
  "offlineSessionMaxLifespan": 5184000,
  "clientSessionIdleTimeout": 0,
  "clientSessionMaxLifespan": 0,
  "accessCodeLifespan": 60,
  "accessCodeLifespanUserAction": 300,
  "accessCodeLifespanLogin": 1800,
  "actionTokenGeneratedByAdminLifespan": 43200,
  "actionTokenGeneratedByUserLifespan": 300,
  "enabled": true,
  "sslRequired": "external",
  "registrationAllowed": false,
  "registrationEmailAsUsername": false,
  "rememberMe": false,
  "verifyEmail": false,
  "loginWithEmailAllowed": true,
  "duplicateEmailsAllowed": false,
  "resetPasswordAllowed": false,
  "editUsernameAllowed": false,
  "bruteForceProtected": false,
  "permanentLockout": false,
  "maxFailureWaitSeconds": 900,
  "minimumQuickLoginWaitSeconds": 60,
  "waitIncrementSeconds": 60,
  "quickLoginCheckMilliSeconds": 1000,
  "maxDeltaTimeSeconds": 43200,
  "failureFactor": 30,
  "loginTheme": "custom",
  "roles": {
    "realm": [
      {
        "id": "285bde59-2f85-41b9-9d31-eb28dd86cd89",
        "name": "uma_authorization",
        "description": "${role_uma_authorization}",
        "composite": false,
        "clientRole": false,
        "containerId": "master",
        "attributes": {}
      },
      {
        "id": "07b4f9af-fe6e-4f4f-827d-cfc46a6159bd",
        "name": "create-realm",
        "description": "${role_create-realm}",
        "composite": false,
        "clientRole": false,
        "containerId": "master",
        "attributes": {}
      },
      {
        "id": "1118074c-6a67-44fe-9eaf-d119bd7651ca",
        "name": "admin",
        "description": "${role_admin}",
        "composite": true,
        "composites": {
          "realm": [
            "create-realm"
          ],
          "client": {
            "master-realm": [
              "manage-users",
              "query-realms",
              "view-realm",
              "view-events",
              "view-authorization",
              "query-groups",
              "view-users",
              "manage-identity-providers",
              "manage-events",
              "manage-authorization",
              "manage-realm",
              "query-clients",
              "impersonation",
              "manage-clients",
              "view-clients",
              "create-client",
              "view-identity-providers",
              "query-users"
            ],
            "easy-shopping-realm": [
              "manage-authorization",
              "manage-realm",
              "create-client",
              "manage-events",
              "impersonation",
              "view-realm",
              "manage-users",
              "view-users",
              "query-realms",
              "query-users",
              "manage-clients",
              "query-clients",
              "view-clients",
              "query-groups",
              "view-authorization",
              "view-identity-providers",
              "view-events",
              "manage-identity-providers"
            ]
          }
        },
        "clientRole": false,
        "containerId": "master",
        "attributes": {}
      },
      {
        "id": "b9271821-e662-4e7d-a0fe-5b4c198c466e",
        "name": "offline_access",
        "description": "${role_offline-access}",
        "composite": false,
        "clientRole": false,
        "containerId": "master",
        "attributes": {}
      }
    ],
    "client": {
      "security-admin-console": [],
      "admin-cli": [],
      "account-console": [],
      "broker": [
        {
          "id": "31954234-3fc7-4bf0-9a69-07edc1b705e9",
          "name": "read-token",
          "description": "${role_read-token}",
          "composite": false,
          "clientRole": true,
          "containerId": "d226d3b2-ace4-4db6-aa3b-113b220e7358",
          "attributes": {}
        }
      ],
      "master-realm": [
        {
          "id": "24249ba5-3308-45c2-afc1-888b28316340",
          "name": "manage-authorization",
          "description": "${role_manage-authorization}",
          "composite": false,
          "clientRole": true,
          "containerId": "ff1b1c86-742f-4f47-97f3-0650d7c85408",
          "attributes": {}
        },
        {
          "id": "6f87df50-7b67-4670-aaf5-56e667f6892a",
          "name": "manage-realm",
          "description": "${role_manage-realm}",
          "composite": false,
          "clientRole": true,
          "containerId": "ff1b1c86-742f-4f47-97f3-0650d7c85408",
          "attributes": {}
        },
        {
          "id": "c0952a2c-c916-4f1b-84b7-27f8770ec3a9",
          "name": "manage-users",
          "description": "${role_manage-users}",
          "composite": false,
          "clientRole": true,
          "containerId": "ff1b1c86-742f-4f47-97f3-0650d7c85408",
          "attributes": {}
        },
        {
          "id": "91e2126a-f9f3-488b-8c56-99a57c56e006",
          "name": "view-realm",
          "description": "${role_view-realm}",
          "composite": false,
          "clientRole": true,
          "containerId": "ff1b1c86-742f-4f47-97f3-0650d7c85408",
          "attributes": {}
        },
        {
          "id": "5bcc3262-5cd2-47d6-881e-4c8104468dbb",
          "name": "query-realms",
          "description": "${role_query-realms}",
          "composite": false,
          "clientRole": true,
          "containerId": "ff1b1c86-742f-4f47-97f3-0650d7c85408",
          "attributes": {}
        },
        {
          "id": "ebc74769-a86d-42cc-959e-2f78fcb29bae",
          "name": "view-events",
          "description": "${role_view-events}",
          "composite": false,
          "clientRole": true,
          "containerId": "ff1b1c86-742f-4f47-97f3-0650d7c85408",
          "attributes": {}
        },
        {
          "id": "c270cd9d-72a2-40ff-9f9b-c466550148ac",
          "name": "query-clients",
          "description": "${role_query-clients}",
          "composite": false,
          "clientRole": true,
          "containerId": "ff1b1c86-742f-4f47-97f3-0650d7c85408",
          "attributes": {}
        },
        {
          "id": "0d74ad68-bf3b-4abb-81a9-0429573f3162",
          "name": "impersonation",
          "description": "${role_impersonation}",
          "composite": false,
          "clientRole": true,
          "containerId": "ff1b1c86-742f-4f47-97f3-0650d7c85408",
          "attributes": {}
        },
        {
          "id": "a3c8a834-47d9-4663-a597-d91cbd43a1e8",
          "name": "manage-clients",
          "description": "${role_manage-clients}",
          "composite": false,
          "clientRole": true,
          "containerId": "ff1b1c86-742f-4f47-97f3-0650d7c85408",
          "attributes": {}
        },
        {
          "id": "08bc7e85-6893-4228-b019-840e607d6f06",
          "name": "view-clients",
          "description": "${role_view-clients}",
          "composite": true,
          "composites": {
            "client": {
              "master-realm": [
                "query-clients"
              ]
            }
          },
          "clientRole": true,
          "containerId": "ff1b1c86-742f-4f47-97f3-0650d7c85408",
          "attributes": {}
        },
        {
          "id": "4b579bf3-03ed-431a-afb1-e52d4a12f63d",
          "name": "view-authorization",
          "description": "${role_view-authorization}",
          "composite": false,
          "clientRole": true,
          "containerId": "ff1b1c86-742f-4f47-97f3-0650d7c85408",
          "attributes": {}
        },
        {
          "id": "92529ed3-be63-4fef-be3f-13f612078fdc",
          "name": "view-users",
          "description": "${role_view-users}",
          "composite": true,
          "composites": {
            "client": {
              "master-realm": [
                "query-groups",
                "query-users"
              ]
            }
          },
          "clientRole": true,
          "containerId": "ff1b1c86-742f-4f47-97f3-0650d7c85408",
          "attributes": {}
        },
        {
          "id": "39d955e6-0922-470d-90e8-497824dc04f3",
          "name": "query-groups",
          "description": "${role_query-groups}",
          "composite": false,
          "clientRole": true,
          "containerId": "ff1b1c86-742f-4f47-97f3-0650d7c85408",
          "attributes": {}
        },
        {
          "id": "c5ffcfc1-d440-435e-afd0-a4e9c5295583",
          "name": "manage-identity-providers",
          "description": "${role_manage-identity-providers}",
          "composite": false,
          "clientRole": true,
          "containerId": "ff1b1c86-742f-4f47-97f3-0650d7c85408",
          "attributes": {}
        },
        {
          "id": "cce36cc3-f6ac-4372-8b82-569cead7646b",
          "name": "create-client",
          "description": "${role_create-client}",
          "composite": false,
          "clientRole": true,
          "containerId": "ff1b1c86-742f-4f47-97f3-0650d7c85408",
          "attributes": {}
        },
        {
          "id": "f818e570-da94-4f51-96db-b992d2bbdf5d",
          "name": "view-identity-providers",
          "description": "${role_view-identity-providers}",
          "composite": false,
          "clientRole": true,
          "containerId": "ff1b1c86-742f-4f47-97f3-0650d7c85408",
          "attributes": {}
        },
        {
          "id": "f3edee7f-44ed-42d1-8e78-a52748d15326",
          "name": "manage-events",
          "description": "${role_manage-events}",
          "composite": false,
          "clientRole": true,
          "containerId": "ff1b1c86-742f-4f47-97f3-0650d7c85408",
          "attributes": {}
        },
        {
          "id": "ab06172a-0258-4346-8064-926f4a36b6ce",
          "name": "query-users",
          "description": "${role_query-users}",
          "composite": false,
          "clientRole": true,
          "containerId": "ff1b1c86-742f-4f47-97f3-0650d7c85408",
          "attributes": {}
        }
      ],
      "easy-shopping-realm": [
        {
          "id": "14a7278f-cb88-4a51-95b1-465cac4e8d76",
          "name": "query-users",
          "description": "${role_query-users}",
          "composite": false,
          "clientRole": true,
          "containerId": "b2e2b797-0f7e-4300-87e0-bd06a9e6e3e0",
          "attributes": {}
        },
        {
          "id": "155555f9-cf64-4b30-89d5-47eb429d6b1c",
          "name": "manage-clients",
          "description": "${role_manage-clients}",
          "composite": false,
          "clientRole": true,
          "containerId": "b2e2b797-0f7e-4300-87e0-bd06a9e6e3e0",
          "attributes": {}
        },
        {
          "id": "35834fb2-658e-4a1f-ad9d-79a8526113b3",
          "name": "query-clients",
          "description": "${role_query-clients}",
          "composite": false,
          "clientRole": true,
          "containerId": "b2e2b797-0f7e-4300-87e0-bd06a9e6e3e0",
          "attributes": {}
        },
        {
          "id": "66b5bd45-c3e2-4681-bb65-554f3c78d7a1",
          "name": "view-clients",
          "description": "${role_view-clients}",
          "composite": true,
          "composites": {
            "client": {
              "easy-shopping-realm": [
                "query-clients"
              ]
            }
          },
          "clientRole": true,
          "containerId": "b2e2b797-0f7e-4300-87e0-bd06a9e6e3e0",
          "attributes": {}
        },
        {
          "id": "aad2aa51-4183-456c-932b-2b065985d52e",
          "name": "manage-authorization",
          "description": "${role_manage-authorization}",
          "composite": false,
          "clientRole": true,
          "containerId": "b2e2b797-0f7e-4300-87e0-bd06a9e6e3e0",
          "attributes": {}
        },
        {
          "id": "4eec2b59-a0de-497e-9d40-5958cd6a0604",
          "name": "query-groups",
          "description": "${role_query-groups}",
          "composite": false,
          "clientRole": true,
          "containerId": "b2e2b797-0f7e-4300-87e0-bd06a9e6e3e0",
          "attributes": {}
        },
        {
          "id": "08a0717b-483a-4e61-a684-4ea2980fd11b",
          "name": "view-authorization",
          "description": "${role_view-authorization}",
          "composite": false,
          "clientRole": true,
          "containerId": "b2e2b797-0f7e-4300-87e0-bd06a9e6e3e0",
          "attributes": {}
        },
        {
          "id": "82dd5acf-92da-431e-a86a-241f9303c8d7",
          "name": "manage-realm",
          "description": "${role_manage-realm}",
          "composite": false,
          "clientRole": true,
          "containerId": "b2e2b797-0f7e-4300-87e0-bd06a9e6e3e0",
          "attributes": {}
        },
        {
          "id": "47472cf7-131d-4dc7-845e-bdbca99f8ef8",
          "name": "view-identity-providers",
          "description": "${role_view-identity-providers}",
          "composite": false,
          "clientRole": true,
          "containerId": "b2e2b797-0f7e-4300-87e0-bd06a9e6e3e0",
          "attributes": {}
        },
        {
          "id": "e8a08439-16a4-4225-b942-86a0acc4dec3",
          "name": "create-client",
          "description": "${role_create-client}",
          "composite": false,
          "clientRole": true,
          "containerId": "b2e2b797-0f7e-4300-87e0-bd06a9e6e3e0",
          "attributes": {}
        },
        {
          "id": "d7e4e181-bc8e-449d-b322-353e62a7c9e7",
          "name": "view-events",
          "description": "${role_view-events}",
          "composite": false,
          "clientRole": true,
          "containerId": "b2e2b797-0f7e-4300-87e0-bd06a9e6e3e0",
          "attributes": {}
        },
        {
          "id": "80a9c7f6-8df3-4365-965e-4b3ccc1be572",
          "name": "manage-events",
          "description": "${role_manage-events}",
          "composite": false,
          "clientRole": true,
          "containerId": "b2e2b797-0f7e-4300-87e0-bd06a9e6e3e0",
          "attributes": {}
        },
        {
          "id": "d4818ca9-45f6-4ab2-aab5-8baa2a0ee8b0",
          "name": "impersonation",
          "description": "${role_impersonation}",
          "composite": false,
          "clientRole": true,
          "containerId": "b2e2b797-0f7e-4300-87e0-bd06a9e6e3e0",
          "attributes": {}
        },
        {
          "id": "de4413ff-1334-4de1-b927-ad2219f9941d",
          "name": "view-realm",
          "description": "${role_view-realm}",
          "composite": false,
          "clientRole": true,
          "containerId": "b2e2b797-0f7e-4300-87e0-bd06a9e6e3e0",
          "attributes": {}
        },
        {
          "id": "7681d6d2-30b2-4428-ad51-a44f7eeab165",
          "name": "manage-users",
          "description": "${role_manage-users}",
          "composite": false,
          "clientRole": true,
          "containerId": "b2e2b797-0f7e-4300-87e0-bd06a9e6e3e0",
          "attributes": {}
        },
        {
          "id": "2f9fd7cb-83ce-4fb9-82fe-32a0de0e75eb",
          "name": "manage-identity-providers",
          "description": "${role_manage-identity-providers}",
          "composite": false,
          "clientRole": true,
          "containerId": "b2e2b797-0f7e-4300-87e0-bd06a9e6e3e0",
          "attributes": {}
        },
        {
          "id": "3ab9df94-1f8a-44d6-9fba-8a5e1faea9ef",
          "name": "view-users",
          "description": "${role_view-users}",
          "composite": true,
          "composites": {
            "client": {
              "easy-shopping-realm": [
                "query-users",
                "query-groups"
              ]
            }
          },
          "clientRole": true,
          "containerId": "b2e2b797-0f7e-4300-87e0-bd06a9e6e3e0",
          "attributes": {}
        },
        {
          "id": "896ec8aa-cd9e-46dd-bbb3-f470de29bd4e",
          "name": "query-realms",
          "description": "${role_query-realms}",
          "composite": false,
          "clientRole": true,
          "containerId": "b2e2b797-0f7e-4300-87e0-bd06a9e6e3e0",
          "attributes": {}
        }
      ],
      "account": [
        {
          "id": "6f6a4977-d909-4d27-b68c-d9bc6735b6e8",
          "name": "manage-account-links",
          "description": "${role_manage-account-links}",
          "composite": false,
          "clientRole": true,
          "containerId": "b2aa0833-f7e8-4fd7-92bf-8107a2818932",
          "attributes": {}
        },
        {
          "id": "608a3e9f-64da-41ea-ab3f-4777583903b1",
          "name": "manage-account",
          "description": "${role_manage-account}",
          "composite": true,
          "composites": {
            "client": {
              "account": [
                "manage-account-links"
              ]
            }
          },
          "clientRole": true,
          "containerId": "b2aa0833-f7e8-4fd7-92bf-8107a2818932",
          "attributes": {}
        },
        {
          "id": "609005b0-b6e8-4e57-b0fb-0549a58fb18a",
          "name": "view-profile",
          "description": "${role_view-profile}",
          "composite": false,
          "clientRole": true,
          "containerId": "b2aa0833-f7e8-4fd7-92bf-8107a2818932",
          "attributes": {}
        },
        {
          "id": "fbe277ed-0e2f-43a2-b7f7-3914824b85bf",
          "name": "view-applications",
          "description": "${role_view-applications}",
          "composite": false,
          "clientRole": true,
          "containerId": "b2aa0833-f7e8-4fd7-92bf-8107a2818932",
          "attributes": {}
        },
        {
          "id": "43e2a2cb-af0d-4905-88dc-9fa9bb49f7fd",
          "name": "manage-consent",
          "description": "${role_manage-consent}",
          "composite": true,
          "composites": {
            "client": {
              "account": [
                "view-consent"
              ]
            }
          },
          "clientRole": true,
          "containerId": "b2aa0833-f7e8-4fd7-92bf-8107a2818932",
          "attributes": {}
        },
        {
          "id": "2285758f-ff44-49bc-834d-0c2ca64647e8",
          "name": "view-consent",
          "description": "${role_view-consent}",
          "composite": false,
          "clientRole": true,
          "containerId": "b2aa0833-f7e8-4fd7-92bf-8107a2818932",
          "attributes": {}
        }
      ]
    }
  },
  "groups": [],
  "defaultRoles": [
    "uma_authorization",
    "offline_access"
  ],
  "requiredCredentials": [
    "password"
  ],
  "otpPolicyType": "totp",
  "otpPolicyAlgorithm": "HmacSHA1",
  "otpPolicyInitialCounter": 0,
  "otpPolicyDigits": 6,
  "otpPolicyLookAheadWindow": 1,
  "otpPolicyPeriod": 30,
  "otpSupportedApplications": [
    "FreeOTP",
    "Google Authenticator"
  ],
  "webAuthnPolicyRpEntityName": "keycloak",
  "webAuthnPolicySignatureAlgorithms": [
    "ES256"
  ],
  "webAuthnPolicyRpId": "",
  "webAuthnPolicyAttestationConveyancePreference": "not specified",
  "webAuthnPolicyAuthenticatorAttachment": "not specified",
  "webAuthnPolicyRequireResidentKey": "not specified",
  "webAuthnPolicyUserVerificationRequirement": "not specified",
  "webAuthnPolicyCreateTimeout": 0,
  "webAuthnPolicyAvoidSameAuthenticatorRegister": false,
  "webAuthnPolicyAcceptableAaguids": [],
  "webAuthnPolicyPasswordlessRpEntityName": "keycloak",
  "webAuthnPolicyPasswordlessSignatureAlgorithms": [
    "ES256"
  ],
  "webAuthnPolicyPasswordlessRpId": "",
  "webAuthnPolicyPasswordlessAttestationConveyancePreference": "not specified",
  "webAuthnPolicyPasswordlessAuthenticatorAttachment": "not specified",
  "webAuthnPolicyPasswordlessRequireResidentKey": "not specified",
  "webAuthnPolicyPasswordlessUserVerificationRequirement": "not specified",
  "webAuthnPolicyPasswordlessCreateTimeout": 0,
  "webAuthnPolicyPasswordlessAvoidSameAuthenticatorRegister": false,
  "webAuthnPolicyPasswordlessAcceptableAaguids": [],
  "scopeMappings": [
    {
      "clientScope": "offline_access",
      "roles": [
        "offline_access"
      ]
    }
  ],
  "clientScopeMappings": {
    "account": [
      {
        "client": "account-console",
        "roles": [
          "manage-account"
        ]
      }
    ]
  },
  "clients": [
    {
      "id": "b2aa0833-f7e8-4fd7-92bf-8107a2818932",
      "clientId": "account",
      "name": "${client_account}",
      "rootUrl": "${authBaseUrl}",
      "baseUrl": "/realms/master/account/",
      "surrogateAuthRequired": false,
      "enabled": true,
      "alwaysDisplayInConsole": false,
      "clientAuthenticatorType": "client-secret",
      "secret": "**********",
      "defaultRoles": [
        "manage-account",
        "view-profile"
      ],
      "redirectUris": [
        "/realms/master/account/*"
      ],
      "webOrigins": [],
      "notBefore": 0,
      "bearerOnly": false,
      "consentRequired": false,
      "standardFlowEnabled": true,
      "implicitFlowEnabled": false,
      "directAccessGrantsEnabled": false,
      "serviceAccountsEnabled": false,
      "publicClient": false,
      "frontchannelLogout": false,
      "protocol": "openid-connect",
      "attributes": {},
      "authenticationFlowBindingOverrides": {},
      "fullScopeAllowed": false,
      "nodeReRegistrationTimeout": 0,
      "defaultClientScopes": [
        "web-origins",
        "role_list",
        "roles",
        "profile",
        "email"
      ],
      "optionalClientScopes": [
        "address",
        "phone",
        "offline_access",
        "microprofile-jwt"
      ]
    },
    {
      "id": "9517e36d-0bed-4666-bcd2-2851daab08f5",
      "clientId": "account-console",
      "name": "${client_account-console}",
      "rootUrl": "${authBaseUrl}",
      "baseUrl": "/realms/master/account/",
      "surrogateAuthRequired": false,
      "enabled": true,
      "alwaysDisplayInConsole": false,
      "clientAuthenticatorType": "client-secret",
      "secret": "**********",
      "redirectUris": [
        "/realms/master/account/*"
      ],
      "webOrigins": [],
      "notBefore": 0,
      "bearerOnly": false,
      "consentRequired": false,
      "standardFlowEnabled": true,
      "implicitFlowEnabled": false,
      "directAccessGrantsEnabled": false,
      "serviceAccountsEnabled": false,
      "publicClient": true,
      "frontchannelLogout": false,
      "protocol": "openid-connect",
      "attributes": {
        "pkce.code.challenge.method": "S256"
      },
      "authenticationFlowBindingOverrides": {},
      "fullScopeAllowed": false,
      "nodeReRegistrationTimeout": 0,
      "protocolMappers": [
        {
          "id": "95c14027-2249-4343-a4ca-4f00b832a983",
          "name": "audience resolve",
          "protocol": "openid-connect",
          "protocolMapper": "oidc-audience-resolve-mapper",
          "consentRequired": false,
          "config": {}
        }
      ],
      "defaultClientScopes": [
        "web-origins",
        "role_list",
        "roles",
        "profile",
        "email"
      ],
      "optionalClientScopes": [
        "address",
        "phone",
        "offline_access",
        "microprofile-jwt"
      ]
    },
    {
      "id": "c0d3e75c-b486-48ca-b320-9faf5f348c48",
      "clientId": "admin-cli",
      "name": "${client_admin-cli}",
      "surrogateAuthRequired": false,
      "enabled": true,
      "alwaysDisplayInConsole": false,
      "clientAuthenticatorType": "client-secret",
      "secret": "**********",
      "redirectUris": [],
      "webOrigins": [],
      "notBefore": 0,
      "bearerOnly": false,
      "consentRequired": false,
      "standardFlowEnabled": false,
      "implicitFlowEnabled": false,
      "directAccessGrantsEnabled": true,
      "serviceAccountsEnabled": false,
      "publicClient": true,
      "frontchannelLogout": false,
      "protocol": "openid-connect",
      "attributes": {},
      "authenticationFlowBindingOverrides": {},
      "fullScopeAllowed": false,
      "nodeReRegistrationTimeout": 0,
      "defaultClientScopes": [
        "web-origins",
        "role_list",
        "roles",
        "profile",
        "email"
      ],
      "optionalClientScopes": [
        "address",
        "phone",
        "offline_access",
        "microprofile-jwt"
      ]
    },
    {
      "id": "d226d3b2-ace4-4db6-aa3b-113b220e7358",
      "clientId": "broker",
      "name": "${client_broker}",
      "surrogateAuthRequired": false,
      "enabled": true,
      "alwaysDisplayInConsole": false,
      "clientAuthenticatorType": "client-secret",
      "secret": "**********",
      "redirectUris": [],
      "webOrigins": [],
      "notBefore": 0,
      "bearerOnly": false,
      "consentRequired": false,
      "standardFlowEnabled": true,
      "implicitFlowEnabled": false,
      "directAccessGrantsEnabled": false,
      "serviceAccountsEnabled": false,
      "publicClient": false,
      "frontchannelLogout": false,
      "protocol": "openid-connect",
      "attributes": {},
      "authenticationFlowBindingOverrides": {},
      "fullScopeAllowed": false,
      "nodeReRegistrationTimeout": 0,
      "defaultClientScopes": [
        "web-origins",
        "role_list",
        "roles",
        "profile",
        "email"
      ],
      "optionalClientScopes": [
        "address",
        "phone",
        "offline_access",
        "microprofile-jwt"
      ]
    },
    {
      "id": "b2e2b797-0f7e-4300-87e0-bd06a9e6e3e0",
      "clientId": "easy-shopping-realm",
      "name": "easy-shopping Realm",
      "surrogateAuthRequired": false,
      "enabled": true,
      "alwaysDisplayInConsole": false,
      "clientAuthenticatorType": "client-secret",
      "secret": "**********",
      "redirectUris": [],
      "webOrigins": [],
      "notBefore": 0,
      "bearerOnly": true,
      "consentRequired": false,
      "standardFlowEnabled": true,
      "implicitFlowEnabled": false,
      "directAccessGrantsEnabled": false,
      "serviceAccountsEnabled": false,
      "publicClient": false,
      "frontchannelLogout": false,
      "attributes": {},
      "authenticationFlowBindingOverrides": {},
      "fullScopeAllowed": true,
      "nodeReRegistrationTimeout": 0,
      "defaultClientScopes": [
        "web-origins",
        "role_list",
        "roles",
        "profile",
        "email"
      ],
      "optionalClientScopes": [
        "address",
        "phone",
        "offline_access",
        "microprofile-jwt"
      ]
    },
    {
      "id": "ff1b1c86-742f-4f47-97f3-0650d7c85408",
      "clientId": "master-realm",
      "name": "master Realm",
      "surrogateAuthRequired": false,
      "enabled": true,
      "alwaysDisplayInConsole": false,
      "clientAuthenticatorType": "client-secret",
      "secret": "**********",
      "redirectUris": [],
      "webOrigins": [],
      "notBefore": 0,
      "bearerOnly": true,
      "consentRequired": false,
      "standardFlowEnabled": true,
      "implicitFlowEnabled": false,
      "directAccessGrantsEnabled": false,
      "serviceAccountsEnabled": false,
      "publicClient": false,
      "frontchannelLogout": false,
      "attributes": {},
      "authenticationFlowBindingOverrides": {},
      "fullScopeAllowed": true,
      "nodeReRegistrationTimeout": 0,
      "defaultClientScopes": [
        "web-origins",
        "role_list",
        "roles",
        "profile",
        "email"
      ],
      "optionalClientScopes": [
        "address",
        "phone",
        "offline_access",
        "microprofile-jwt"
      ]
    },
    {
      "id": "142582c8-cfbd-479f-87d4-1004535e3705",
      "clientId": "security-admin-console",
      "name": "${client_security-admin-console}",
      "rootUrl": "${authAdminUrl}",
      "baseUrl": "/admin/master/console/",
      "surrogateAuthRequired": false,
      "enabled": true,
      "alwaysDisplayInConsole": false,
      "clientAuthenticatorType": "client-secret",
      "secret": "**********",
      "redirectUris": [
        "/admin/master/console/*"
      ],
      "webOrigins": [
        "+"
      ],
      "notBefore": 0,
      "bearerOnly": false,
      "consentRequired": false,
      "standardFlowEnabled": true,
      "implicitFlowEnabled": false,
      "directAccessGrantsEnabled": false,
      "serviceAccountsEnabled": false,
      "publicClient": true,
      "frontchannelLogout": false,
      "protocol": "openid-connect",
      "attributes": {
        "pkce.code.challenge.method": "S256"
      },
      "authenticationFlowBindingOverrides": {},
      "fullScopeAllowed": false,
      "nodeReRegistrationTimeout": 0,
      "protocolMappers": [
        {
          "id": "fa98fbfd-09ce-42d9-9665-337c1eee72e2",
          "name": "locale",
          "protocol": "openid-connect",
          "protocolMapper": "oidc-usermodel-attribute-mapper",
          "consentRequired": false,
          "config": {
            "userinfo.token.claim": "true",
            "user.attribute": "locale",
            "id.token.claim": "true",
            "access.token.claim": "true",
            "claim.name": "locale",
            "jsonType.label": "String"
          }
        }
      ],
      "defaultClientScopes": [
        "web-origins",
        "role_list",
        "roles",
        "profile",
        "email"
      ],
      "optionalClientScopes": [
        "address",
        "phone",
        "offline_access",
        "microprofile-jwt"
      ]
    }
  ],
  "clientScopes": [
    {
      "id": "e3329c3f-78cd-4c5a-8785-6d9128ad6e17",
      "name": "address",
      "description": "OpenID Connect built-in scope: address",
      "protocol": "openid-connect",
      "attributes": {
        "include.in.token.scope": "true",
        "display.on.consent.screen": "true",
        "consent.screen.text": "${addressScopeConsentText}"
      },
      "protocolMappers": [
        {
          "id": "8da1d9fd-9771-4e70-a3e8-42fddf32b5cd",
          "name": "address",
          "protocol": "openid-connect",
          "protocolMapper": "oidc-address-mapper",
          "consentRequired": false,
          "config": {
            "user.attribute.formatted": "formatted",
            "user.attribute.country": "country",
            "user.attribute.postal_code": "postal_code",
            "userinfo.token.claim": "true",
            "user.attribute.street": "street",
            "id.token.claim": "true",
            "user.attribute.region": "region",
            "access.token.claim": "true",
            "user.attribute.locality": "locality"
          }
        }
      ]
    },
    {
      "id": "f7de33ee-13eb-4c6f-a612-3de3f2df2c6a",
      "name": "email",
      "description": "OpenID Connect built-in scope: email",
      "protocol": "openid-connect",
      "attributes": {
        "include.in.token.scope": "true",
        "display.on.consent.screen": "true",
        "consent.screen.text": "${emailScopeConsentText}"
      },
      "protocolMappers": [
        {
          "id": "26629d6a-7968-4dfc-bf30-a911e54eacb7",
          "name": "email verified",
          "protocol": "openid-connect",
          "protocolMapper": "oidc-usermodel-property-mapper",
          "consentRequired": false,
          "config": {
            "userinfo.token.claim": "true",
            "user.attribute": "emailVerified",
            "id.token.claim": "true",
            "access.token.claim": "true",
            "claim.name": "email_verified",
            "jsonType.label": "boolean"
          }
        },
        {
          "id": "2c829d25-e7e1-4fd8-a4e1-16efefcec631",
          "name": "email",
          "protocol": "openid-connect",
          "protocolMapper": "oidc-usermodel-property-mapper",
          "consentRequired": false,
          "config": {
            "userinfo.token.claim": "true",
            "user.attribute": "email",
            "id.token.claim": "true",
            "access.token.claim": "true",
            "claim.name": "email",
            "jsonType.label": "String"
          }
        }
      ]
    },
    {
      "id": "267bfaa5-46f7-4f93-aaf1-8ef762a04004",
      "name": "microprofile-jwt",
      "description": "Microprofile - JWT built-in scope",
      "protocol": "openid-connect",
      "attributes": {
        "include.in.token.scope": "true",
        "display.on.consent.screen": "false"
      },
      "protocolMappers": [
        {
          "id": "6afea019-d213-4c27-8cd4-e929a7df330e",
          "name": "upn",
          "protocol": "openid-connect",
          "protocolMapper": "oidc-usermodel-property-mapper",
          "consentRequired": false,
          "config": {
            "userinfo.token.claim": "true",
            "user.attribute": "username",
            "id.token.claim": "true",
            "access.token.claim": "true",
            "claim.name": "upn",
            "jsonType.label": "String"
          }
        },
        {
          "id": "7373d6f6-39e6-4ff6-881f-10c6dbe4087d",
          "name": "groups",
          "protocol": "openid-connect",
          "protocolMapper": "oidc-usermodel-realm-role-mapper",
          "consentRequired": false,
          "config": {
            "multivalued": "true",
            "user.attribute": "foo",
            "id.token.claim": "true",
            "access.token.claim": "true",
            "claim.name": "groups",
            "jsonType.label": "String"
          }
        }
      ]
    },
    {
      "id": "5c2ab8fe-26f0-4d82-a8ca-1ba2c754347c",
      "name": "offline_access",
      "description": "OpenID Connect built-in scope: offline_access",
      "protocol": "openid-connect",
      "attributes": {
        "consent.screen.text": "${offlineAccessScopeConsentText}",
        "display.on.consent.screen": "true"
      }
    },
    {
      "id": "3f3cd2d9-33ea-4b0b-9d40-343afc1ec741",
      "name": "phone",
      "description": "OpenID Connect built-in scope: phone",
      "protocol": "openid-connect",
      "attributes": {
        "include.in.token.scope": "true",
        "display.on.consent.screen": "true",
        "consent.screen.text": "${phoneScopeConsentText}"
      },
      "protocolMappers": [
        {
          "id": "d8a18c76-3f1a-437f-b500-387d06ce29f2",
          "name": "phone number",
          "protocol": "openid-connect",
          "protocolMapper": "oidc-usermodel-attribute-mapper",
          "consentRequired": false,
          "config": {
            "userinfo.token.claim": "true",
            "user.attribute": "phoneNumber",
            "id.token.claim": "true",
            "access.token.claim": "true",
            "claim.name": "phone_number",
            "jsonType.label": "String"
          }
        },
        {
          "id": "907c2b9c-363d-4b5d-8189-199afd1acf12",
          "name": "phone number verified",
          "protocol": "openid-connect",
          "protocolMapper": "oidc-usermodel-attribute-mapper",
          "consentRequired": false,
          "config": {
            "userinfo.token.claim": "true",
            "user.attribute": "phoneNumberVerified",
            "id.token.claim": "true",
            "access.token.claim": "true",
            "claim.name": "phone_number_verified",
            "jsonType.label": "boolean"
          }
        }
      ]
    },
    {
      "id": "5b978420-e8ae-4a7c-becf-5d0db998b896",
      "name": "profile",
      "description": "OpenID Connect built-in scope: profile",
      "protocol": "openid-connect",
      "attributes": {
        "include.in.token.scope": "true",
        "display.on.consent.screen": "true",
        "consent.screen.text": "${profileScopeConsentText}"
      },
      "protocolMappers": [
        {
          "id": "d39926af-ddcd-44e0-bbb0-d4317eaef835",
          "name": "gender",
          "protocol": "openid-connect",
          "protocolMapper": "oidc-usermodel-attribute-mapper",
          "consentRequired": false,
          "config": {
            "userinfo.token.claim": "true",
            "user.attribute": "gender",
            "id.token.claim": "true",
            "access.token.claim": "true",
            "claim.name": "gender",
            "jsonType.label": "String"
          }
        },
        {
          "id": "c4cc6190-62b3-4273-876f-7d5ebef9a6b0",
          "name": "locale",
          "protocol": "openid-connect",
          "protocolMapper": "oidc-usermodel-attribute-mapper",
          "consentRequired": false,
          "config": {
            "userinfo.token.claim": "true",
            "user.attribute": "locale",
            "id.token.claim": "true",
            "access.token.claim": "true",
            "claim.name": "locale",
            "jsonType.label": "String"
          }
        },
        {
          "id": "849193d0-0644-432d-b672-3d3a8094d2d0",
          "name": "website",
          "protocol": "openid-connect",
          "protocolMapper": "oidc-usermodel-attribute-mapper",
          "consentRequired": false,
          "config": {
            "userinfo.token.claim": "true",
            "user.attribute": "website",
            "id.token.claim": "true",
            "access.token.claim": "true",
            "claim.name": "website",
            "jsonType.label": "String"
          }
        },
        {
          "id": "74f48575-07ee-4859-8d23-73b58cd6cddc",
          "name": "middle name",
          "protocol": "openid-connect",
          "protocolMapper": "oidc-usermodel-attribute-mapper",
          "consentRequired": false,
          "config": {
            "userinfo.token.claim": "true",
            "user.attribute": "middleName",
            "id.token.claim": "true",
            "access.token.claim": "true",
            "claim.name": "middle_name",
            "jsonType.label": "String"
          }
        },
        {
          "id": "20f6e9ce-aa93-484e-ba28-ffcef1d69501",
          "name": "nickname",
          "protocol": "openid-connect",
          "protocolMapper": "oidc-usermodel-attribute-mapper",
          "consentRequired": false,
          "config": {
            "userinfo.token.claim": "true",
            "user.attribute": "nickname",
            "id.token.claim": "true",
            "access.token.claim": "true",
            "claim.name": "nickname",
            "jsonType.label": "String"
          }
        },
        {
          "id": "894c905b-e23e-453a-8257-7a2886b58f59",
          "name": "birthdate",
          "protocol": "openid-connect",
          "protocolMapper": "oidc-usermodel-attribute-mapper",
          "consentRequired": false,
          "config": {
            "userinfo.token.claim": "true",
            "user.attribute": "birthdate",
            "id.token.claim": "true",
            "access.token.claim": "true",
            "claim.name": "birthdate",
            "jsonType.label": "String"
          }
        },
        {
          "id": "75c64a27-904f-486e-a8c3-d880d40341a1",
          "name": "updated at",
          "protocol": "openid-connect",
          "protocolMapper": "oidc-usermodel-attribute-mapper",
          "consentRequired": false,
          "config": {
            "userinfo.token.claim": "true",
            "user.attribute": "updatedAt",
            "id.token.claim": "true",
            "access.token.claim": "true",
            "claim.name": "updated_at",
            "jsonType.label": "String"
          }
        },
        {
          "id": "07c5247e-eefe-4cfc-ac4c-0d5c91de103d",
          "name": "given name",
          "protocol": "openid-connect",
          "protocolMapper": "oidc-usermodel-property-mapper",
          "consentRequired": false,
          "config": {
            "userinfo.token.claim": "true",
            "user.attribute": "firstName",
            "id.token.claim": "true",
            "access.token.claim": "true",
            "claim.name": "given_name",
            "jsonType.label": "String"
          }
        },
        {
          "id": "bd7d918c-f37c-43a5-9f6d-0bf774e5a630",
          "name": "username",
          "protocol": "openid-connect",
          "protocolMapper": "oidc-usermodel-property-mapper",
          "consentRequired": false,
          "config": {
            "userinfo.token.claim": "true",
            "user.attribute": "username",
            "id.token.claim": "true",
            "access.token.claim": "true",
            "claim.name": "preferred_username",
            "jsonType.label": "String"
          }
        },
        {
          "id": "2546aab7-8b80-491a-91f5-e4ef1372d068",
          "name": "family name",
          "protocol": "openid-connect",
          "protocolMapper": "oidc-usermodel-property-mapper",
          "consentRequired": false,
          "config": {
            "userinfo.token.claim": "true",
            "user.attribute": "lastName",
            "id.token.claim": "true",
            "access.token.claim": "true",
            "claim.name": "family_name",
            "jsonType.label": "String"
          }
        },
        {
          "id": "ea89478f-550c-4ec5-addc-f6b223090d8a",
          "name": "picture",
          "protocol": "openid-connect",
          "protocolMapper": "oidc-usermodel-attribute-mapper",
          "consentRequired": false,
          "config": {
            "userinfo.token.claim": "true",
            "user.attribute": "picture",
            "id.token.claim": "true",
            "access.token.claim": "true",
            "claim.name": "picture",
            "jsonType.label": "String"
          }
        },
        {
          "id": "d1f7dced-f7c0-4cb1-8492-f0c760b2bcab",
          "name": "profile",
          "protocol": "openid-connect",
          "protocolMapper": "oidc-usermodel-attribute-mapper",
          "consentRequired": false,
          "config": {
            "userinfo.token.claim": "true",
            "user.attribute": "profile",
            "id.token.claim": "true",
            "access.token.claim": "true",
            "claim.name": "profile",
            "jsonType.label": "String"
          }
        },
        {
          "id": "a86016cb-6a08-46aa-9463-0553a0520a89",
          "name": "zoneinfo",
          "protocol": "openid-connect",
          "protocolMapper": "oidc-usermodel-attribute-mapper",
          "consentRequired": false,
          "config": {
            "userinfo.token.claim": "true",
            "user.attribute": "zoneinfo",
            "id.token.claim": "true",
            "access.token.claim": "true",
            "claim.name": "zoneinfo",
            "jsonType.label": "String"
          }
        },
        {
          "id": "0e562c46-dc62-4de1-9d5f-545917d1be3f",
          "name": "full name",
          "protocol": "openid-connect",
          "protocolMapper": "oidc-full-name-mapper",
          "consentRequired": false,
          "config": {
            "id.token.claim": "true",
            "access.token.claim": "true",
            "userinfo.token.claim": "true"
          }
        }
      ]
    },
    {
      "id": "11a4ad84-b731-4ded-8901-b8dc7f87bbfb",
      "name": "role_list",
      "description": "SAML role list",
      "protocol": "saml",
      "attributes": {
        "consent.screen.text": "${samlRoleListScopeConsentText}",
        "display.on.consent.screen": "true"
      },
      "protocolMappers": [
        {
          "id": "4c795eb5-a98c-425a-86aa-91c7c5bd2a8e",
          "name": "role list",
          "protocol": "saml",
          "protocolMapper": "saml-role-list-mapper",
          "consentRequired": false,
          "config": {
            "single": "false",
            "attribute.nameformat": "Basic",
            "attribute.name": "Role"
          }
        }
      ]
    },
    {
      "id": "b8c7312a-71ea-4333-833c-6b9d8cea1965",
      "name": "roles",
      "description": "OpenID Connect scope for add user roles to the access token",
      "protocol": "openid-connect",
      "attributes": {
        "include.in.token.scope": "false",
        "display.on.consent.screen": "true",
        "consent.screen.text": "${rolesScopeConsentText}"
      },
      "protocolMappers": [
        {
          "id": "25eaa6ba-4daa-4ccb-a0d7-845e969d81db",
          "name": "realm roles",
          "protocol": "openid-connect",
          "protocolMapper": "oidc-usermodel-realm-role-mapper",
          "consentRequired": false,
          "config": {
            "user.attribute": "foo",
            "access.token.claim": "true",
            "claim.name": "realm_access.roles",
            "jsonType.label": "String",
            "multivalued": "true"
          }
        },
        {
          "id": "c7f8e5ca-60ce-4e03-9f0e-7b45747f0811",
          "name": "client roles",
          "protocol": "openid-connect",
          "protocolMapper": "oidc-usermodel-client-role-mapper",
          "consentRequired": false,
          "config": {
            "user.attribute": "foo",
            "access.token.claim": "true",
            "claim.name": "resource_access.${client_id}.roles",
            "jsonType.label": "String",
            "multivalued": "true"
          }
        },
        {
          "id": "095aa181-6974-4302-9f10-839df94d7883",
          "name": "audience resolve",
          "protocol": "openid-connect",
          "protocolMapper": "oidc-audience-resolve-mapper",
          "consentRequired": false,
          "config": {}
        }
      ]
    },
    {
      "id": "3d9bd620-1f76-4d0d-a6cf-43783bfd4bbe",
      "name": "web-origins",
      "description": "OpenID Connect scope for add allowed web origins to the access token",
      "protocol": "openid-connect",
      "attributes": {
        "include.in.token.scope": "false",
        "display.on.consent.screen": "false",
        "consent.screen.text": ""
      },
      "protocolMappers": [
        {
          "id": "9ca85f3f-ab08-4141-a74b-cd8fd7c2d2ea",
          "name": "allowed web origins",
          "protocol": "openid-connect",
          "protocolMapper": "oidc-allowed-origins-mapper",
          "consentRequired": false,
          "config": {}
        }
      ]
    }
  ],
  "defaultDefaultClientScopes": [
    "role_list",
    "profile",
    "email",
    "roles",
    "web-origins"
  ],
  "defaultOptionalClientScopes": [
    "offline_access",
    "address",
    "phone",
    "microprofile-jwt"
  ],
  "browserSecurityHeaders": {
    "contentSecurityPolicyReportOnly": "",
    "xContentTypeOptions": "nosniff",
    "xRobotsTag": "none",
    "xFrameOptions": "SAMEORIGIN",
    "xXSSProtection": "1; mode=block",
    "contentSecurityPolicy": "frame-src 'self'; frame-ancestors 'self'; object-src 'none';",
    "strictTransportSecurity": "max-age=31536000; includeSubDomains"
  },
  "smtpServer": {},
  "eventsEnabled": false,
  "eventsListeners": [
    "jboss-logging"
  ],
  "enabledEventTypes": [],
  "adminEventsEnabled": false,
  "adminEventsDetailsEnabled": false,
  "components": {
    "org.keycloak.services.clientregistration.policy.ClientRegistrationPolicy": [
      {
        "id": "77c93e73-1b34-47be-a294-04451a48a425",
        "name": "Trusted Hosts",
        "providerId": "trusted-hosts",
        "subType": "anonymous",
        "subComponents": {},
        "config": {
          "host-sending-registration-request-must-match": [
            "true"
          ],
          "client-uris-must-match": [
            "true"
          ]
        }
      },
      {
        "id": "80e01a82-a0bf-4785-b6e6-fa72343fea56",
        "name": "Allowed Protocol Mapper Types",
        "providerId": "allowed-protocol-mappers",
        "subType": "anonymous",
        "subComponents": {},
        "config": {
          "allowed-protocol-mapper-types": [
            "saml-user-property-mapper",
            "oidc-usermodel-property-mapper",
            "oidc-full-name-mapper",
            "oidc-sha256-pairwise-sub-mapper",
            "oidc-usermodel-attribute-mapper",
            "saml-role-list-mapper",
            "saml-user-attribute-mapper",
            "oidc-address-mapper"
          ]
        }
      },
      {
        "id": "7a31070a-7f8e-4513-b13e-05074b3f114a",
        "name": "Consent Required",
        "providerId": "consent-required",
        "subType": "anonymous",
        "subComponents": {},
        "config": {}
      },
      {
        "id": "8350d8d8-2741-42d1-82b0-cfe79ac91ceb",
        "name": "Max Clients Limit",
        "providerId": "max-clients",
        "subType": "anonymous",
        "subComponents": {},
        "config": {
          "max-clients": [
            "200"
          ]
        }
      },
      {
        "id": "4f422981-1ed1-4096-badb-4ddb86aa74b6",
        "name": "Allowed Protocol Mapper Types",
        "providerId": "allowed-protocol-mappers",
        "subType": "authenticated",
        "subComponents": {},
        "config": {
          "allowed-protocol-mapper-types": [
            "saml-user-attribute-mapper",
            "oidc-usermodel-property-mapper",
            "oidc-sha256-pairwise-sub-mapper",
            "saml-user-property-mapper",
            "oidc-usermodel-attribute-mapper",
            "oidc-address-mapper",
            "saml-role-list-mapper",
            "oidc-full-name-mapper"
          ]
        }
      },
      {
        "id": "5298b590-dfc6-4b6f-8f95-e31c5a1471f3",
        "name": "Allowed Client Scopes",
        "providerId": "allowed-client-templates",
        "subType": "anonymous",
        "subComponents": {},
        "config": {
          "allow-default-scopes": [
            "true"
          ]
        }
      },
      {
        "id": "e7517f32-3aff-4a9f-a08a-91d86702f4c4",
        "name": "Full Scope Disabled",
        "providerId": "scope",
        "subType": "anonymous",
        "subComponents": {},
        "config": {}
      },
      {
        "id": "1b2eafd2-dcbe-4240-a35b-bbd38054844c",
        "name": "Allowed Client Scopes",
        "providerId": "allowed-client-templates",
        "subType": "authenticated",
        "subComponents": {},
        "config": {
          "allow-default-scopes": [
            "true"
          ]
        }
      }
    ],
    "org.keycloak.keys.KeyProvider": [
      {
        "id": "c419edff-cc49-414d-8bdd-04a6ebd7689d",
        "name": "fallback-HS256",
        "providerId": "hmac-generated",
        "subComponents": {},
        "config": {
          "priority": [
            "-100"
          ],
          "algorithm": [
            "HS256"
          ]
        }
      },
      {
        "id": "3ba4ecac-5aac-4664-9033-01c2a5da2b2b",
        "name": "fallback-RS256",
        "providerId": "rsa-generated",
        "subComponents": {},
        "config": {
          "priority": [
            "-100"
          ],
          "algorithm": [
            "RS256"
          ]
        }
      }
    ]
  },
  "internationalizationEnabled": false,
  "supportedLocales": [],
  "authenticationFlows": [
    {
      "id": "5e463fac-fc19-4351-818c-d7479f82dfaa",
      "alias": "Account verification options",
      "description": "Method with which to verity the existing account",
      "providerId": "basic-flow",
      "topLevel": false,
      "builtIn": true,
      "authenticationExecutions": [
        {
          "authenticator": "idp-email-verification",
          "requirement": "ALTERNATIVE",
          "priority": 10,
          "userSetupAllowed": false,
          "autheticatorFlow": false
        },
        {
          "requirement": "ALTERNATIVE",
          "priority": 20,
          "flowAlias": "Verify Existing Account by Re-authentication",
          "userSetupAllowed": false,
          "autheticatorFlow": true
        }
      ]
    },
    {
      "id": "b61782fc-4cee-46f3-b4e5-ce5d71f8891c",
      "alias": "Authentication Options",
      "description": "Authentication options.",
      "providerId": "basic-flow",
      "topLevel": false,
      "builtIn": true,
      "authenticationExecutions": [
        {
          "authenticator": "basic-auth",
          "requirement": "REQUIRED",
          "priority": 10,
          "userSetupAllowed": false,
          "autheticatorFlow": false
        },
        {
          "authenticator": "basic-auth-otp",
          "requirement": "DISABLED",
          "priority": 20,
          "userSetupAllowed": false,
          "autheticatorFlow": false
        },
        {
          "authenticator": "auth-spnego",
          "requirement": "DISABLED",
          "priority": 30,
          "userSetupAllowed": false,
          "autheticatorFlow": false
        }
      ]
    },
    {
      "id": "79416ec7-bbe9-42ba-8d8d-9cdb660c1b00",
      "alias": "Browser - Conditional OTP",
      "description": "Flow to determine if the OTP is required for the authentication",
      "providerId": "basic-flow",
      "topLevel": false,
      "builtIn": true,
      "authenticationExecutions": [
        {
          "authenticator": "conditional-user-configured",
          "requirement": "REQUIRED",
          "priority": 10,
          "userSetupAllowed": false,
          "autheticatorFlow": false
        },
        {
          "authenticator": "auth-otp-form",
          "requirement": "REQUIRED",
          "priority": 20,
          "userSetupAllowed": false,
          "autheticatorFlow": false
        }
      ]
    },
    {
      "id": "4ba4d215-67e9-437e-ba1e-70677c9b3f75",
      "alias": "Direct Grant - Conditional OTP",
      "description": "Flow to determine if the OTP is required for the authentication",
      "providerId": "basic-flow",
      "topLevel": false,
      "builtIn": true,
      "authenticationExecutions": [
        {
          "authenticator": "conditional-user-configured",
          "requirement": "REQUIRED",
          "priority": 10,
          "userSetupAllowed": false,
          "autheticatorFlow": false
        },
        {
          "authenticator": "direct-grant-validate-otp",
          "requirement": "REQUIRED",
          "priority": 20,
          "userSetupAllowed": false,
          "autheticatorFlow": false
        }
      ]
    },
    {
      "id": "7a730045-0d89-4863-9d5c-9a07e80859e0",
      "alias": "First broker login - Conditional OTP",
      "description": "Flow to determine if the OTP is required for the authentication",
      "providerId": "basic-flow",
      "topLevel": false,
      "builtIn": true,
      "authenticationExecutions": [
        {
          "authenticator": "conditional-user-configured",
          "requirement": "REQUIRED",
          "priority": 10,
          "userSetupAllowed": false,
          "autheticatorFlow": false
        },
        {
          "authenticator": "auth-otp-form",
          "requirement": "REQUIRED",
          "priority": 20,
          "userSetupAllowed": false,
          "autheticatorFlow": false
        }
      ]
    },
    {
      "id": "dcbbced4-0798-4a7f-83db-d03aa6d9a5d5",
      "alias": "Handle Existing Account",
      "description": "Handle what to do if there is existing account with same email/username like authenticated identity provider",
      "providerId": "basic-flow",
      "topLevel": false,
      "builtIn": true,
      "authenticationExecutions": [
        {
          "authenticator": "idp-confirm-link",
          "requirement": "REQUIRED",
          "priority": 10,
          "userSetupAllowed": false,
          "autheticatorFlow": false
        },
        {
          "requirement": "REQUIRED",
          "priority": 20,
          "flowAlias": "Account verification options",
          "userSetupAllowed": false,
          "autheticatorFlow": true
        }
      ]
    },
    {
      "id": "f7939f22-0c6a-4a09-a6e7-264fb20a07ca",
      "alias": "Reset - Conditional OTP",
      "description": "Flow to determine if the OTP should be reset or not. Set to REQUIRED to force.",
      "providerId": "basic-flow",
      "topLevel": false,
      "builtIn": true,
      "authenticationExecutions": [
        {
          "authenticator": "conditional-user-configured",
          "requirement": "REQUIRED",
          "priority": 10,
          "userSetupAllowed": false,
          "autheticatorFlow": false
        },
        {
          "authenticator": "reset-otp",
          "requirement": "REQUIRED",
          "priority": 20,
          "userSetupAllowed": false,
          "autheticatorFlow": false
        }
      ]
    },
    {
      "id": "070fcf1f-6ee1-4b69-9a19-23bd13c12d16",
      "alias": "User creation or linking",
      "description": "Flow for the existing/non-existing user alternatives",
      "providerId": "basic-flow",
      "topLevel": false,
      "builtIn": true,
      "authenticationExecutions": [
        {
          "authenticatorConfig": "create unique user config",
          "authenticator": "idp-create-user-if-unique",
          "requirement": "ALTERNATIVE",
          "priority": 10,
          "userSetupAllowed": false,
          "autheticatorFlow": false
        },
        {
          "requirement": "ALTERNATIVE",
          "priority": 20,
          "flowAlias": "Handle Existing Account",
          "userSetupAllowed": false,
          "autheticatorFlow": true
        }
      ]
    },
    {
      "id": "7d180270-6e45-4baa-826d-003b3f1d2afd",
      "alias": "Verify Existing Account by Re-authentication",
      "description": "Reauthentication of existing account",
      "providerId": "basic-flow",
      "topLevel": false,
      "builtIn": true,
      "authenticationExecutions": [
        {
          "authenticator": "idp-username-password-form",
          "requirement": "REQUIRED",
          "priority": 10,
          "userSetupAllowed": false,
          "autheticatorFlow": false
        },
        {
          "requirement": "CONDITIONAL",
          "priority": 20,
          "flowAlias": "First broker login - Conditional OTP",
          "userSetupAllowed": false,
          "autheticatorFlow": true
        }
      ]
    },
    {
      "id": "615074dd-c604-4b56-bbbd-b29078728d7c",
      "alias": "browser",
      "description": "browser based authentication",
      "providerId": "basic-flow",
      "topLevel": true,
      "builtIn": true,
      "authenticationExecutions": [
        {
          "authenticator": "auth-cookie",
          "requirement": "ALTERNATIVE",
          "priority": 10,
          "userSetupAllowed": false,
          "autheticatorFlow": false
        },
        {
          "authenticator": "auth-spnego",
          "requirement": "DISABLED",
          "priority": 20,
          "userSetupAllowed": false,
          "autheticatorFlow": false
        },
        {
          "authenticator": "identity-provider-redirector",
          "requirement": "ALTERNATIVE",
          "priority": 25,
          "userSetupAllowed": false,
          "autheticatorFlow": false
        },
        {
          "requirement": "ALTERNATIVE",
          "priority": 30,
          "flowAlias": "forms",
          "userSetupAllowed": false,
          "autheticatorFlow": true
        }
      ]
    },
    {
      "id": "38e17056-f254-4849-8cf8-4a753fba327b",
      "alias": "clients",
      "description": "Base authentication for clients",
      "providerId": "client-flow",
      "topLevel": true,
      "builtIn": true,
      "authenticationExecutions": [
        {
          "authenticator": "client-secret",
          "requirement": "ALTERNATIVE",
          "priority": 10,
          "userSetupAllowed": false,
          "autheticatorFlow": false
        },
        {
          "authenticator": "client-jwt",
          "requirement": "ALTERNATIVE",
          "priority": 20,
          "userSetupAllowed": false,
          "autheticatorFlow": false
        },
        {
          "authenticator": "client-secret-jwt",
          "requirement": "ALTERNATIVE",
          "priority": 30,
          "userSetupAllowed": false,
          "autheticatorFlow": false
        },
        {
          "authenticator": "client-x509",
          "requirement": "ALTERNATIVE",
          "priority": 40,
          "userSetupAllowed": false,
          "autheticatorFlow": false
        }
      ]
    },
    {
      "id": "269b83d3-50d8-4c2a-9d4e-11979b019993",
      "alias": "direct grant",
      "description": "OpenID Connect Resource Owner Grant",
      "providerId": "basic-flow",
      "topLevel": true,
      "builtIn": true,
      "authenticationExecutions": [
        {
          "authenticator": "direct-grant-validate-username",
          "requirement": "REQUIRED",
          "priority": 10,
          "userSetupAllowed": false,
          "autheticatorFlow": false
        },
        {
          "authenticator": "direct-grant-validate-password",
          "requirement": "REQUIRED",
          "priority": 20,
          "userSetupAllowed": false,
          "autheticatorFlow": false
        },
        {
          "requirement": "CONDITIONAL",
          "priority": 30,
          "flowAlias": "Direct Grant - Conditional OTP",
          "userSetupAllowed": false,
          "autheticatorFlow": true
        }
      ]
    },
    {
      "id": "e85c8530-2758-49a8-9f1e-9830ac628b4d",
      "alias": "docker auth",
      "description": "Used by Docker clients to authenticate against the IDP",
      "providerId": "basic-flow",
      "topLevel": true,
      "builtIn": true,
      "authenticationExecutions": [
        {
          "authenticator": "docker-http-basic-authenticator",
          "requirement": "REQUIRED",
          "priority": 10,
          "userSetupAllowed": false,
          "autheticatorFlow": false
        }
      ]
    },
    {
      "id": "0fc033dd-ec32-46bd-b9a4-aa4fb366b6de",
      "alias": "first broker login",
      "description": "Actions taken after first broker login with identity provider account, which is not yet linked to any Keycloak account",
      "providerId": "basic-flow",
      "topLevel": true,
      "builtIn": true,
      "authenticationExecutions": [
        {
          "authenticatorConfig": "review profile config",
          "authenticator": "idp-review-profile",
          "requirement": "REQUIRED",
          "priority": 10,
          "userSetupAllowed": false,
          "autheticatorFlow": false
        },
        {
          "requirement": "REQUIRED",
          "priority": 20,
          "flowAlias": "User creation or linking",
          "userSetupAllowed": false,
          "autheticatorFlow": true
        }
      ]
    },
    {
      "id": "f5f9696a-3ba2-4c31-9305-8cba1671cbee",
      "alias": "forms",
      "description": "Username, password, otp and other auth forms.",
      "providerId": "basic-flow",
      "topLevel": false,
      "builtIn": true,
      "authenticationExecutions": [
        {
          "authenticator": "auth-username-password-form",
          "requirement": "REQUIRED",
          "priority": 10,
          "userSetupAllowed": false,
          "autheticatorFlow": false
        },
        {
          "requirement": "CONDITIONAL",
          "priority": 20,
          "flowAlias": "Browser - Conditional OTP",
          "userSetupAllowed": false,
          "autheticatorFlow": true
        }
      ]
    },
    {
      "id": "dd0c8261-8d71-460c-b4f1-e79537653953",
      "alias": "http challenge",
      "description": "An authentication flow based on challenge-response HTTP Authentication Schemes",
      "providerId": "basic-flow",
      "topLevel": true,
      "builtIn": true,
      "authenticationExecutions": [
        {
          "authenticator": "no-cookie-redirect",
          "requirement": "REQUIRED",
          "priority": 10,
          "userSetupAllowed": false,
          "autheticatorFlow": false
        },
        {
          "requirement": "REQUIRED",
          "priority": 20,
          "flowAlias": "Authentication Options",
          "userSetupAllowed": false,
          "autheticatorFlow": true
        }
      ]
    },
    {
      "id": "c1aaf6c4-a9bb-4b46-9717-17b0e5565093",
      "alias": "registration",
      "description": "registration flow",
      "providerId": "basic-flow",
      "topLevel": true,
      "builtIn": true,
      "authenticationExecutions": [
        {
          "authenticator": "registration-page-form",
          "requirement": "REQUIRED",
          "priority": 10,
          "flowAlias": "registration form",
          "userSetupAllowed": false,
          "autheticatorFlow": true
        }
      ]
    },
    {
      "id": "52b921e1-7cc1-4760-830d-f3f68061fa4b",
      "alias": "registration form",
      "description": "registration form",
      "providerId": "form-flow",
      "topLevel": false,
      "builtIn": true,
      "authenticationExecutions": [
        {
          "authenticator": "registration-user-creation",
          "requirement": "REQUIRED",
          "priority": 20,
          "userSetupAllowed": false,
          "autheticatorFlow": false
        },
        {
          "authenticator": "registration-profile-action",
          "requirement": "REQUIRED",
          "priority": 40,
          "userSetupAllowed": false,
          "autheticatorFlow": false
        },
        {
          "authenticator": "registration-password-action",
          "requirement": "REQUIRED",
          "priority": 50,
          "userSetupAllowed": false,
          "autheticatorFlow": false
        },
        {
          "authenticator": "registration-recaptcha-action",
          "requirement": "DISABLED",
          "priority": 60,
          "userSetupAllowed": false,
          "autheticatorFlow": false
        }
      ]
    },
    {
      "id": "a0c036ff-1f5d-443b-94df-c2dec97a3017",
      "alias": "reset credentials",
      "description": "Reset credentials for a user if they forgot their password or something",
      "providerId": "basic-flow",
      "topLevel": true,
      "builtIn": true,
      "authenticationExecutions": [
        {
          "authenticator": "reset-credentials-choose-user",
          "requirement": "REQUIRED",
          "priority": 10,
          "userSetupAllowed": false,
          "autheticatorFlow": false
        },
        {
          "authenticator": "reset-credential-email",
          "requirement": "REQUIRED",
          "priority": 20,
          "userSetupAllowed": false,
          "autheticatorFlow": false
        },
        {
          "authenticator": "reset-password",
          "requirement": "REQUIRED",
          "priority": 30,
          "userSetupAllowed": false,
          "autheticatorFlow": false
        },
        {
          "requirement": "CONDITIONAL",
          "priority": 40,
          "flowAlias": "Reset - Conditional OTP",
          "userSetupAllowed": false,
          "autheticatorFlow": true
        }
      ]
    },
    {
      "id": "b6ff966c-f25a-48ea-abe2-9339b420d7cd",
      "alias": "saml ecp",
      "description": "SAML ECP Profile Authentication Flow",
      "providerId": "basic-flow",
      "topLevel": true,
      "builtIn": true,
      "authenticationExecutions": [
        {
          "authenticator": "http-basic-authenticator",
          "requirement": "REQUIRED",
          "priority": 10,
          "userSetupAllowed": false,
          "autheticatorFlow": false
        }
      ]
    }
  ],
  "authenticatorConfig": [
    {
      "id": "fa7b69f7-b3ad-4f81-b2d2-c31ee947e20e",
      "alias": "create unique user config",
      "config": {
        "require.password.update.after.registration": "false"
      }
    },
    {
      "id": "c3244672-11ad-4b1b-b534-a6f4390d377e",
      "alias": "review profile config",
      "config": {
        "update.profile.on.first.login": "missing"
      }
    }
  ],
  "requiredActions": [
    {
      "alias": "CONFIGURE_TOTP",
      "name": "Configure OTP",
      "providerId": "CONFIGURE_TOTP",
      "enabled": true,
      "defaultAction": false,
      "priority": 10,
      "config": {}
    },
    {
      "alias": "terms_and_conditions",
      "name": "Terms and Conditions",
      "providerId": "terms_and_conditions",
      "enabled": false,
      "defaultAction": false,
      "priority": 20,
      "config": {}
    },
    {
      "alias": "UPDATE_PASSWORD",
      "name": "Update Password",
      "providerId": "UPDATE_PASSWORD",
      "enabled": true,
      "defaultAction": false,
      "priority": 30,
      "config": {}
    },
    {
      "alias": "UPDATE_PROFILE",
      "name": "Update Profile",
      "providerId": "UPDATE_PROFILE",
      "enabled": true,
      "defaultAction": false,
      "priority": 40,
      "config": {}
    },
    {
      "alias": "VERIFY_EMAIL",
      "name": "Verify Email",
      "providerId": "VERIFY_EMAIL",
      "enabled": true,
      "defaultAction": false,
      "priority": 50,
      "config": {}
    },
    {
      "alias": "update_user_locale",
      "name": "Update User Locale",
      "providerId": "update_user_locale",
      "enabled": true,
      "defaultAction": false,
      "priority": 1000,
      "config": {}
    }
  ],
  "browserFlow": "browser",
  "registrationFlow": "registration",
  "directGrantFlow": "direct grant",
  "resetCredentialsFlow": "reset credentials",
  "clientAuthenticationFlow": "clients",
  "dockerAuthenticationFlow": "docker auth",
  "attributes": {},
  "keycloakVersion": "11.0.2",
  "userManagedAccessAllowed": false
}